library3D/__init__.py
library3D/core.py
library3D/demo.py
library3D/graphics.py
library3D/math3d.py
3dlibrary-0.2.dist-info/METADATA
3dlibrary-0.2.dist-info/WHEEL
3dlibrary-0.2.dist-info/top_level.txt
3dlibrary-0.2.dist-info/RECORD
