Metadata-Version: 2.4
Name: 3dlibrary
Version: 0.2
Summary: Saf Python 3D kütüphanesi (OpenGL kullanmadan, v0.2)
Home-page: https://github.com/kullaniciadi/3dlibrary
Author: Mehmet
Classifier: Programming Language :: Python :: 3
Classifier: License :: OSI Approved :: MIT License
Classifier: Operating System :: OS Independent
Requires-Python: >=3.7
Requires-Dist: Pillow
Dynamic: author
Dynamic: classifier
Dynamic: description
Dynamic: description-content-type
Dynamic: home-page
Dynamic: requires-dist
Dynamic: requires-python
Dynamic: summary
